<annotation>
	<folder></folder>
	<filename>b63df6a03f_jpg.rf.e4ff97781f3f6c5357c6dfb26f63dd34.jpg</filename>
	<path>b63df6a03f_jpg.rf.e4ff97781f3f6c5357c6dfb26f63dd34.jpg</path>
	<source>
		<database>roboflow.com</database>
	</source>
	<size>
		<width>217</width>
		<height>132</height>
		<depth>3</depth>
	</size>
	<segmented>0</segmented>
	<object>
		<name>Cars</name>
		<pose>Unspecified</pose>
		<truncated>0</truncated>
		<difficult>0</difficult>
		<occluded>0</occluded>
		<bndbox>
			<xmin>1</xmin>
			<xmax>216</xmax>
			<ymin>3</ymin>
			<ymax>128</ymax>
		</bndbox>
		<polygon>
			<x1>2.119140625</x1>
			<y1>63.3623046875</y1>
			<x2>0</x2>
			<y2>93.4541015625</y2>
			<x3>3.814453125</x3>
			<y3>104.8974609375</y3>
			<x4>14.1982421875</x4>
			<y4>113.5859375</y4>
			<x5>52.7666015625</x5>
			<y5>125.876953125</y5>
			<x6>103.2021484375</x6>
			<y6>126.724609375</y6>
			<x7>117.6123046875</x7>
			<y7>122.0625</y7>
			<x8>129.9033203125</x8>
			<y8>125.453125</y8>
			<x9>137.744140625</x9>
			<y9>121.4267578125</y9>
			<x10>146.8564453125</x10>
			<y10>104.26171875</y10>
			<x11>193.9013671875</x11>
			<y11>78.83203125</y11>
			<x12>206.404296875</x12>
			<y12>80.3154296875</y12>
			<x13>213.609375</x13>
			<y13>57.8525390625</y13>
			<x14>215.3046875</x14>
			<y14>33.2705078125</y14>
			<x15>200.6826171875</x15>
			<y15>16.953125</y15>
			<x16>184.1533203125</x16>
			<y16>6.78125</y16>
			<x17>163.3857421875</x17>
			<y17>3.390625</y17>
			<x18>157.4521484375</x18>
			<y18>6.357421875</y18>
			<x19>144.3134765625</x19>
			<y19>2.119140625</y19>
			<x20>103.2021484375</x20>
			<y20>3.390625</y20>
			<x21>90.0634765625</x21>
			<y21>7.205078125</y21>
			<x22>6.9931640625</x22>
			<y22>52.130859375</y22>
		</polygon>
	</object>
</annotation>
